reactomepy/__init__.py
reactomepy/code/__init__.py
reactomepy/code/describe_pathway.py
reactomepy/code/neo4jnode.py
reactomepy/code/neo4jnodebasic.py
reactomepy/code/relationships.py
reactomepy/code/species.py
reactomepy/code/taxid2genbankcommonname.py
reactomepy/code/utils.py
reactomepy/code/cli/__init__.py
reactomepy/code/enrich/__init__.py
reactomepy/code/enrich/enrich_pwy.py
reactomepy/code/ex/__init__.py
reactomepy/code/ex/uniprot_accession_list.py
reactomepy/code/node/__init__.py
reactomepy/code/node/abstractmodifiedresidue.py
reactomepy/code/node/affiliation.py
reactomepy/code/node/blackboxevent.py
reactomepy/code/node/book.py
reactomepy/code/node/candidateset.py
reactomepy/code/node/catalystactivity.py
reactomepy/code/node/chemicaldrug.py
reactomepy/code/node/compartment.py
reactomepy/code/node/complex.py
reactomepy/code/node/crosslinkedresidue.py
reactomepy/code/node/databaseidentifier.py
reactomepy/code/node/databaseobject.py
reactomepy/code/node/dbinfo.py
reactomepy/code/node/definedset.py
reactomepy/code/node/depolymerisation.py
reactomepy/code/node/drug.py
reactomepy/code/node/entityfunctionalstatus.py
reactomepy/code/node/entityset.py
reactomepy/code/node/entitywithaccessionedsequence.py
reactomepy/code/node/event.py
reactomepy/code/node/externalontology.py
reactomepy/code/node/failedreaction.py
reactomepy/code/node/figure.py
reactomepy/code/node/format.py
reactomepy/code/node/fragmentdeletionmodification.py
reactomepy/code/node/fragmentinsertionmodification.py
reactomepy/code/node/fragmentmodification.py
reactomepy/code/node/fragmentreplacedmodification.py
reactomepy/code/node/functionalstatus.py
reactomepy/code/node/functionalstatustype.py
reactomepy/code/node/geneticallymodifiedresidue.py
reactomepy/code/node/genomeencodedentity.py
reactomepy/code/node/go_biologicalprocess.py
reactomepy/code/node/go_cellularcomponent.py
reactomepy/code/node/go_molecularfunction.py
reactomepy/code/node/go_term.py
reactomepy/code/node/groupmodifiedresidue.py
reactomepy-0.68.9.dist-info/LICENSE
reactomepy-0.68.9.dist-info/METADATA
reactomepy-0.68.9.dist-info/WHEEL
reactomepy-0.68.9.dist-info/top_level.txt
reactomepy-0.68.9.dist-info/RECORD
