Metadata-Version: 2.1
Name: reactomepy
Version: 0.68.9
Summary: Explore biomolecular pathways in Reactome from the command line
Home-page: http://github.com/dvklopfenstein/ReactomePy
Author: DV Klopfenstein
Author-email: dvklopfenstein@gmail.com
License: UNKNOWN
Platform: UNKNOWN
Classifier: Development Status :: 4 - Beta
Classifier: Intended Audience :: Science/Research
Classifier: License :: OSI Approved :: BSD License
Classifier: Programming Language :: Python :: 3
Classifier: Topic :: Scientific/Engineering :: Bio-Informatics
Classifier: Operating System :: OS Independent
Requires-Dist: enrichmentanalysis-dvklopfenstein
Requires-Dist: requests
